amsterdamumcdb/__init__.py
amsterdamumcdb/amsterdamumcdb.py
amsterdamumcdb/bigquery.py
amsterdamumcdb/cohorts.py
amsterdamumcdb/connections.py
amsterdamumcdb/dictionary.py
amsterdamumcdb/fluidbalance.py
amsterdamumcdb/plotting.py
amsterdamumcdb/scores.py
amsterdamumcdb/util.py
amsterdamumcdb/dictionary/dictionary.csv
amsterdamumcdb/dictionary/legacy/dictionary.csv
amsterdamumcdb/sql/common/legacy/bilirubin.sql
amsterdamumcdb/sql/common/legacy/creatinine_acute_kidney_injury_failure.sql
amsterdamumcdb/sql/common/legacy/gcs.sql
amsterdamumcdb/sql/common/legacy/heart_rate.sql
amsterdamumcdb/sql/common/legacy/hematocrit.sql
amsterdamumcdb/sql/common/legacy/lactate.sql
amsterdamumcdb/sql/common/legacy/mean_abp.sql
amsterdamumcdb/sql/common/legacy/oxygen_device.sql
amsterdamumcdb/sql/common/legacy/pH.sql
amsterdamumcdb/sql/common/legacy/pO2_FiO2_estimated.sql
amsterdamumcdb/sql/common/legacy/pO2_pCO2_FiO2.sql
amsterdamumcdb/sql/common/legacy/platelets.sql
amsterdamumcdb/sql/common/legacy/potassium.sql
amsterdamumcdb/sql/common/legacy/resp_rate.sql
amsterdamumcdb/sql/common/legacy/sodium.sql
amsterdamumcdb/sql/common/legacy/temperature.sql
amsterdamumcdb/sql/common/legacy/urine_output.sql
amsterdamumcdb/sql/common/legacy/vasopressors_inotropes.sql
amsterdamumcdb/sql/common/legacy/wbc.sql
amsterdamumcdb/sql/diagnosis/cardiac_arrest.sql
amsterdamumcdb/sql/diagnosis/cardiac_surgery.sql
amsterdamumcdb/sql/diagnosis/cardio.sql
amsterdamumcdb/sql/diagnosis/gastro_intestinal_surgery.sql
amsterdamumcdb/sql/diagnosis/infection.sql
amsterdamumcdb/sql/diagnosis/medical.sql
amsterdamumcdb/sql/diagnosis/neuro.sql
amsterdamumcdb/sql/diagnosis/neurosurgery.sql
amsterdamumcdb/sql/diagnosis/reason_for_admission.sql
amsterdamumcdb/sql/diagnosis/respiratory_failure.sql
amsterdamumcdb/sql/diagnosis/surgical.sql
amsterdamumcdb/sql/diagnosis/trauma.sql
amsterdamumcdb/sql/diagnosis/vascular_surgery.sql
amsterdamumcdb/sql/diagnosis/legacy/reason_for_admission.sql
amsterdamumcdb-0.3.1.dist-info/LICENSE
amsterdamumcdb-0.3.1.dist-info/METADATA
amsterdamumcdb-0.3.1.dist-info/WHEEL
amsterdamumcdb-0.3.1.dist-info/top_level.txt
amsterdamumcdb-0.3.1.dist-info/RECORD
