Metadata-Version: 2.2
Name: amsterdamumcdb
Version: 0.3.1
Summary: Common functions for data exploration on AmsterdamUMCdb
Home-page: https://github.com/AmsterdamUMC/AmsterdamUMCdb
Author: Amsterdam UMC Center for Critical Care Computational Intelligence
Author-email: p.thoral@amsterdamumc.nl
Project-URL: Bug Tracker, https://github.com/AmsterdamUMC/AmsterdamUMCdb/issues
Keywords: AmsterdamUMCdb,Intensive Care unit,Critical Care,Medical,Patient Data
Classifier: Development Status :: 3 - Alpha
Classifier: Intended Audience :: Science/Research
Classifier: Intended Audience :: Healthcare Industry
Classifier: Topic :: Scientific/Engineering :: Medical Science Apps.
Classifier: License :: OSI Approved :: MIT License
Classifier: Programming Language :: Python :: 3
Classifier: Programming Language :: Python :: 3.4
Classifier: Programming Language :: Python :: 3.5
Classifier: Programming Language :: Python :: 3.6
Classifier: Programming Language :: Python :: 3.7
Classifier: Programming Language :: Python :: 3.8
Classifier: Programming Language :: Python :: 3.9
Classifier: Programming Language :: Python :: 3.10
Requires-Python: >=3
License-File: LICENSE
Requires-Dist: numpy
Requires-Dist: matplotlib
Dynamic: requires-dist
